django_jasmine/__init__.py
django_jasmine/__init__.pyc
django_jasmine/apps.py
django_jasmine/settings.py
django_jasmine/settings.pyc
django_jasmine/urls.py
django_jasmine/urls.pyc
django_jasmine/views.py
django_jasmine/views.pyc
django_jasmine/__pycache__/__init__.cpython-32.pyc
django_jasmine/__pycache__/__init__.cpython-33.pyc
django_jasmine/__pycache__/__init__.cpython-34.pyc
django_jasmine/__pycache__/__init__.cpython-35.pyc
django_jasmine/__pycache__/settings.cpython-34.pyc
django_jasmine/__pycache__/settings.cpython-35.pyc
django_jasmine/__pycache__/urls.cpython-32.pyc
django_jasmine/__pycache__/urls.cpython-33.pyc
django_jasmine/__pycache__/urls.cpython-34.pyc
django_jasmine/__pycache__/urls.cpython-35.pyc
django_jasmine/__pycache__/views.cpython-32.pyc
django_jasmine/__pycache__/views.cpython-33.pyc
django_jasmine/__pycache__/views.cpython-34.pyc
django_jasmine/__pycache__/views.cpython-35.pyc
django_jasmine/static/.DS_Store
django_jasmine/static/jasmine-jquery-latest.js
django_jasmine/static/jasmine-jquery.1.3.1.js
django_jasmine/static/jasmine-1.0.1/MIT.LICENSE
django_jasmine/static/jasmine-1.0.1/jasmine-html.js
django_jasmine/static/jasmine-1.0.1/jasmine.css
django_jasmine/static/jasmine-1.0.1/jasmine.js
django_jasmine/static/jasmine-1.1.0.rc1/MIT.LICENSE
django_jasmine/static/jasmine-1.1.0.rc1/jasmine-html.js
django_jasmine/static/jasmine-1.1.0.rc1/jasmine.css
django_jasmine/static/jasmine-1.1.0.rc1/jasmine.js
django_jasmine/static/jasmine-1.1.0.rc1/jasmine_favicon.png
django_jasmine/static/jasmine-latest/MIT.LICENSE
django_jasmine/static/jasmine-latest/jasmine-html.js
django_jasmine/static/jasmine-latest/jasmine.css
django_jasmine/static/jasmine-latest/jasmine.js
django_jasmine/static/jasmine-latest/jasmine_favicon.png
django_jasmine/templates/jasmine/base.html
django_jasmine/templates/jasmine/index.html
django_jasmine-0.5.0.dist-info/DESCRIPTION.rst
django_jasmine-0.5.0.dist-info/METADATA
django_jasmine-0.5.0.dist-info/RECORD
django_jasmine-0.5.0.dist-info/WHEEL
django_jasmine-0.5.0.dist-info/metadata.json
django_jasmine-0.5.0.dist-info/pbr.json
django_jasmine-0.5.0.dist-info/top_level.txt
