Metadata-Version: 2.0
Name: django-jasmine
Version: 0.5.0
Summary: Jasmine Javascript testing integration for Django.
Home-page: https://github.com/jakeharding/django-jasmine
Author: Jake Harding
Author-email: jacobeharding@gmail.com
License: BSD
Keywords: django javascript test
Platform: UNKNOWN
Classifier: Development Status :: 4 - Beta
Classifier: Environment :: Web Environment
Classifier: Framework :: Django
Classifier: Intended Audience :: Developers
Classifier: License :: OSI Approved :: BSD License
Classifier: Operating System :: OS Independent
Classifier: Programming Language :: Python
Classifier: Programming Language :: JavaScript
Classifier: Topic :: Internet :: WWW/HTTP :: Dynamic Content
Classifier: Topic :: Software Development :: Testing
Requires-Dist: Django (>=1.8)
